<SQLStatements>
  <stmt>
    <key>key</key>
    <MSSQL />
    <ORACLE />
    <COMMON />
    <JET />
  </stmt>
  <stmt>
    <key>selectall</key>
    <ORACLE>SELECT JOB_ID,JOB_TITLE,MIN_SALARY,MAX_SALARY,CREATE_DATE,UPDATE_DATE,CREATE_USER,UPDATE_USER FROM "JOBS"</ORACLE>
  </stmt>
  <stmt>
    <key>selectone</key>
    <ORACLE>SELECT JOB_ID,JOB_TITLE,MIN_SALARY,MAX_SALARY,CREATE_DATE,UPDATE_DATE,CREATE_USER,UPDATE_USER FROM "JOBS" WHERE JOB_ID=:0</ORACLE>
  </stmt>
  <stmt>
    <key>delete</key>
    <ORACLE>DELETE FROM "JOBS" WHERE JOB_ID=:0</ORACLE>
  </stmt>
  <stmt>
    <key>insert</key>
    <ORACLE>BEGIN insert into "JOBS" (
JOB_TITLE,MIN_SALARY,MAX_SALARY,CREATE_DATE,UPDATE_DATE,CREATE_USER,UPDATE_USER) values (:JOB_TITLE,:MIN_SALARY,:MAX_SALARY,:CREATE_DATE,:UPDATE_DATE,:CREATE_USER,:UPDATE_USER) RETURNING JOB_ID INTO :JOB_ID;END;</ORACLE>
  </stmt>
  <stmt>
    <key>update</key>
    <ORACLE>UPDATE "JOBS" SET JOB_ID=:JOB_ID,JOB_TITLE=:JOB_TITLE,MIN_SALARY=:MIN_SALARY,MAX_SALARY=:MAX_SALARY,CREATE_DATE=:CREATE_DATE,UPDATE_DATE=:UPDATE_DATE,CREATE_USER=:CREATE_USER,UPDATE_USER=:UPDATE_USER WHERE JOB_ID=:JOB_ID</ORACLE>
  </stmt>
</SQLStatements>